{
  "@context": {
    "@vocab": "https://gs1.github.io/EPCIS/",
    "epcis": "https://gs1.github.io/EPCIS/",
    "cbv": "https://ref.gs1.org/cbv/",
    "type": "@type",
    "id": "@id",
    "eventID": "@id"
  },
  "type": "EPCISDocument",
  "schemaVersion": "2.0",
  "creationDate": "2026-05-07T21:32:25.530Z",
  "epcisBody": {
    "eventList": [
      {
        "eventID": "urn:uuid:d51cc07c-ff7d-550f-9aa7-f4e51c1f7582",
        "type": "ObjectEvent",
        "eventTime": "2026-05-12T08:12:00.000Z",
        "eventTimeZoneOffset": "+00:00",
        "epcList": [
          "urn:acme:bike:item:BIKE-2026-W18-0001"
        ],
        "action": "ADD",
        "bizStep": "https://ref.gs1.org/cbv/BizStep-assembling",
        "disposition": "https://ref.gs1.org/cbv/Disp-in_progress",
        "readPoint": {
          "id": "urn:acme:bike:station:FrameWelding"
        },
        "bizLocation": {
          "id": "urn:acme:bike:station:FrameWelding"
        }
      }
    ]
  }
}
